vinnter_hil/__init__.py
vinnter_hil/gpio_wrapper.py
vinnter_hil/hardware_interaction.py
vinnter_hil/serial_wrapper.py
example_dankersw_vinnter_hil-0.0.5.dist-info/METADATA
example_dankersw_vinnter_hil-0.0.5.dist-info/WHEEL
example_dankersw_vinnter_hil-0.0.5.dist-info/top_level.txt
example_dankersw_vinnter_hil-0.0.5.dist-info/RECORD
