Metadata-Version: 2.1
Name: example-dankersw-vinnter-hil
Version: 0.0.5
Summary: a package to interact with the HIL platform
Home-page: UNKNOWN
Author: Wouter Dankers
Author-email: wouter.dankers@vinnter.se
License: UNKNOWN
Platform: UNKNOWN
Classifier: Programming Language :: Python :: 3
Classifier: License :: OSI Approved :: MIT License
Classifier: Operating System :: OS Independent
Requires-Python: >=3.6
